exp_kit-0.0.7.dist-info/DESCRIPTION.rst
exp_kit-0.0.7.dist-info/LICENSE.txt
exp_kit-0.0.7.dist-info/METADATA
exp_kit-0.0.7.dist-info/RECORD
exp_kit-0.0.7.dist-info/WHEEL
exp_kit-0.0.7.dist-info/entry_points.txt
exp_kit-0.0.7.dist-info/metadata.json
exp_kit-0.0.7.dist-info/top_level.txt
expkit/__init__.py
expkit/__main__.py
expkit/cli.py
expkit/ls_cluster.py
expkit/new_cluster.py
expkit/rm_cluster.py
expkit/utils.py
