Metadata-Version: 2.0
Name: exp-kit
Version: 0.0.7
Summary: A CLI tool facilitating experimentation on AWS.
Home-page: https://github.com/All-less/exp-kit
Author: All-less
Author-email: all.less.mail@gmail.com
License: UNKNOWN
Keywords: aws
Platform: UNKNOWN
Classifier: Programming Language :: Python :: 3.5
Classifier: Programming Language :: Python :: 3.6
Requires-Dist: click
Requires-Dist: boto3
Requires-Dist: halo
Requires-Dist: pymongo
Requires-Dist: paramiko
Requires-Dist: tabulate
